[
    {
        "title": "pick up kids",
        "text": "at 1:30 and 2:25",
        "id": "379a602b-a947-4a4a-8bff-0ba1a0419fad"
    },
    {
        "title": "tatum' show",
        "text": "6pm at washington",
        "id": "90d2c1ae-be19-4ac0-9148-e50ca6b283bc"
    },
    {
        "title": "note",
        "text": "text",
        "id": "341e7d75-0927-49ee-a5e8-168752038b7b"
    },
    {
        "title": "new note",
        "text": "note text goes here",
        "id": "9d6672ae-7ea0-423b-b1b2-a92937fe8049"
    },
    {
        "title": "eat lunch",
        "text": "mmmmm trail mix",
        "id": "a1161048-0de8-4fad-897f-4ff8e09b1b80"
    },
    {
        "title": "another note",
        "text": "so many notes",
        "id": "7fe62b7f-1d0e-4cdd-b56a-c06c66877365"
    }
]